discloud/__init__.py
discloud/client.py
discloud/discloud.py
discloud/discloud_typing.py
discloud/errors.py
discloud/http.py
discloud/old.py
discloud/utils.py
discloud-1.0.1.dist-info/METADATA
discloud-1.0.1.dist-info/WHEEL
discloud-1.0.1.dist-info/top_level.txt
discloud-1.0.1.dist-info/RECORD
