Metadata-Version: 2.1
Name: discloud
Version: 1.0.1
Summary: DisCloud API Async Wrapper
Home-page: https://github.com/discloud/python-discloud-status
Author: Algueem
License: MIT License
Project-URL: Homepage, https://github.com/discloud/python-discloud-status
Keywords: discloud
Classifier: Development Status :: 5 - Production/Stable
Classifier: Programming Language :: Python :: 3.10
Classifier: License :: OSI Approved :: MIT License
Classifier: License :: OSI Approved :: Apache Software License
Classifier: Operating System :: OS Independent
Requires-Python: >=3.9
Requires-Dist: python-dateutil
Requires-Dist: aiohttp
